{
	"format_version": "1.8.0",
	"animations": {
		"injection_use": {
			"animation_length": 1.75,
			"bones": {
				"torso": {
					"rotation": {
						"0.875": {
							"vector": [0, 0, 0]
						},
						"1.0": {
							"vector": [3, 0, 0],
							"easing": "easeInOutSine"
						},
						"1.125": {
							"vector": [0, 0, 0],
							"easing": "easeInOutSine"
						}
					}
				},
				"head": {
					"rotation": {
						"0.875": {
							"vector": [0, 0, 0]
						},
						"1.0": {
							"vector": [30, 0, 0],
							"easing": "easeInOutSine"
						},
						"1.125": {
							"vector": [22.5, 0, 0],
							"easing": "easeInOutSine"
						},
						"1.375": {
							"vector": [22.5, 0, 0],
							"easing": "easeInOutSine"
						},
						"1.75": {
							"vector": [0, 0, 0],
							"easing": "easeInOutSine"
						}
					}
				},
				"right_arm": {
					"rotation": {
						"0.0": {
							"vector": [0, 0, 0]
						},
						"0.5": {
							"vector": [-106.75836, 12.14414, -65.63721],
							"easing": "linear"
						},
						"0.625": {
							"vector": [-101.75836, 12.14414, -65.63721],
							"easing": "easeInOutSine"
						},
						"0.75": {
							"vector": [-101.75836, 12.14414, -65.63721],
							"easing": "easeInOutSine"
						},
						"1.0": {
							"vector": [8.0634, 21.07593, -68.49762],
							"easing": "easeInOutSine"
						},
						"1.125": {
							"vector": [-6.9366, 21.07593, -68.49762],
							"easing": "easeInOutSine"
						},
						"1.375": {
							"vector": [-6.9366, 21.07593, -68.49762],
							"easing": "easeInOutSine"
						},
						"1.75": {
							"vector": [0, 0, 0],
							"easing": "easeInOutSine"
						}
					},
					"position": {
						"0.75": {
							"vector": [0, 0, 0]
						},
						"0.875": {
							"vector": [-2, -1, -6],
							"easing": "easeInOutSine"
						},
						"1.0": {
							"vector": [-3, -1, -4],
							"easing": "easeInOutSine"
						},
						"1.375": {
							"vector": [-3, -1, -4],
							"easing": "easeInOutSine"
						},
						"1.75": {
							"vector": [0, 0, 0],
							"easing": "easeInOutSine"
						}
					}
				},
				"left_arm": {
					"rotation": {
						"0.875": {
							"vector": [0, 0, 0]
						},
						"1.0": {
							"vector": [0, 0, -10],
							"easing": "easeInOutSine"
						},
						"1.125": {
							"vector": [0, 0, 0],
							"easing": "easeInOutSine"
						}
					}
				},
				"right_leg": {
					"rotation": {
						"0.875": {
							"vector": [0, 0, 0]
						},
						"1.0": {
							"vector": [5, 0, 0],
							"easing": "easeInOutSine"
						},
						"1.125": {
							"vector": [0, 0, 0],
							"easing": "easeInOutSine"
						}
					},
					"position": {
						"0.875": {
							"vector": [0, 0, 0]
						},
						"1.0": {
							"vector": [0, 0, -1],
							"easing": "easeInOutSine"
						},
						"1.125": {
							"vector": [0, 0, 0],
							"easing": "easeInOutSine"
						}
					}
				},
				"left_leg": {
					"rotation": {
						"0.875": {
							"vector": [0, 0, 0]
						},
						"1.0": {
							"vector": [5, 0, 0],
							"easing": "easeInOutSine"
						},
						"1.125": {
							"vector": [0, 0, 0],
							"easing": "easeInOutSine"
						}
					},
					"position": {
						"0.875": {
							"vector": [0, 0, 0]
						},
						"1.0": {
							"vector": [0, 0, -0.5],
							"easing": "easeInOutSine"
						},
						"1.125": {
							"vector": [0, 0, 0],
							"easing": "easeInOutSine"
						}
					}
				}
			}
		},
		"injection_use_alt": {
			"animation_length": 1.75,
			"bones": {
				"torso": {
					"rotation": {
						"0.875": {
							"vector": [0, 0, 0]
						},
						"1.0": {
							"vector": [3, 0, 0],
							"easing": "easeInOutSine"
						},
						"1.125": {
							"vector": [0, 0, 0],
							"easing": "easeInOutSine"
						}
					}
				},
				"head": {
					"rotation": {
						"0.875": {
							"vector": [0, 0, 0]
						},
						"1.0": {
							"vector": [30, 0, 0],
							"easing": "easeInOutSine"
						},
						"1.125": {
							"vector": [22.5, 0, 0],
							"easing": "easeInOutSine"
						},
						"1.375": {
							"vector": [22.5, 0, 0],
							"easing": "easeInOutSine"
						},
						"1.75": {
							"vector": [0, 0, 0],
							"easing": "easeInOutSine"
						}
					}
				},
				"right_arm": {
					"rotation": {
						"0.875": {
							"vector": [0, 0, 0]
						},
						"1.0": {
							"vector": [0, 0, 10],
							"easing": "easeInOutSine"
						},
						"1.125": {
							"vector": [0, 0, 0],
							"easing": "easeInOutSine"
						}
					}
				},
				"left_arm": {
					"rotation": {
						"0.0": {
							"vector": [0, 0, 0]
						},
						"0.5": {
							"vector": [-106.75836, -12.14414, 65.63721],
							"easing": "linear"
						},
						"0.625": {
							"vector": [-101.75836, -12.14414, 65.63721],
							"easing": "easeInOutSine"
						},
						"0.75": {
							"vector": [-101.75836, -12.14414, 65.63721],
							"easing": "easeInOutSine"
						},
						"1.0": {
							"vector": [8.0634, -21.07593, 68.49762],
							"easing": "easeInOutSine"
						},
						"1.125": {
							"vector": [-6.9366, -21.07593, 68.49762],
							"easing": "easeInOutSine"
						},
						"1.375": {
							"vector": [-6.9366, -21.07593, 68.49762],
							"easing": "easeInOutSine"
						},
						"1.75": {
							"vector": [0, 0, 0],
							"easing": "easeInOutSine"
						}
					},
					"position": {
						"0.75": {
							"vector": [0, 0, 0]
						},
						"0.875": {
							"vector": [2, -1, -6],
							"easing": "easeInOutSine"
						},
						"1.0": {
							"vector": [3, -1, -4],
							"easing": "easeInOutSine"
						},
						"1.375": {
							"vector": [3, -1, -4],
							"easing": "easeInOutSine"
						},
						"1.75": {
							"vector": [0, 0, 0],
							"easing": "easeInOutSine"
						}
					}
				},
				"right_leg": {
					"rotation": {
						"0.875": {
							"vector": [0, 0, 0]
						},
						"1.0": {
							"vector": [5, 0, 0],
							"easing": "easeInOutSine"
						},
						"1.125": {
							"vector": [0, 0, 0],
							"easing": "easeInOutSine"
						}
					},
					"position": {
						"0.875": {
							"vector": [0, 0, 0]
						},
						"1.0": {
							"vector": [0, 0, -0.5],
							"easing": "easeInOutSine"
						},
						"1.125": {
							"vector": [0, 0, 0],
							"easing": "easeInOutSine"
						}
					}
				},
				"left_leg": {
					"rotation": {
						"0.875": {
							"vector": [0, 0, 0]
						},
						"1.0": {
							"vector": [5, 0, 0]
						},
						"1.125": {
							"vector": [0, 0, 0]
						}
					},
					"position": {
						"0.875": {
							"vector": [0, 0, 0]
						},
						"1.0": {
							"vector": [0, 0, -1],
							"easing": "easeInOutSine"
						},
						"1.125": {
							"vector": [0, 0, 0],
							"easing": "easeInOutSine"
						}
					}
				}
			}
		}
	}
}